unienv_droid_data/raw/__init__.py
unienv_droid_data/raw/data_index.py
unienv_droid_data/raw/metadata.py
unienv_droid_data/raw/raw_data.py
unienv_droid_data/raw/svo_file.py
unienv_droid-0.0.1a1.dist-info/METADATA
unienv_droid-0.0.1a1.dist-info/WHEEL
unienv_droid-0.0.1a1.dist-info/top_level.txt
unienv_droid-0.0.1a1.dist-info/RECORD
