Metadata-Version: 2.4
Name: unienv_droid
Version: 0.0.1a1
Requires-Python: >=3.10
Requires-Dist: unienv
Requires-Dist: h5py
Requires-Dist: pyserde
